pink_accents/__init__.py
pink_accents/__main__.py
pink_accents/accent.py
pink_accents/cli.py
pink_accents/context.py
pink_accents/errors.py
pink_accents/match.py
pink_accents/py.typed
pink_accents/replacement.py
pink_accents/types.py
pink_accents-0.1.1.dist-info/METADATA
pink_accents-0.1.1.dist-info/WHEEL
pink_accents-0.1.1.dist-info/entry_points.txt
pink_accents-0.1.1.dist-info/licenses/LICENSE
pink_accents-0.1.1.dist-info/RECORD
