Metadata-Version: 2.1
Name: pink_accents
Version: 0.1.1
Summary: Accent system based on string pattern matching
Project-URL: repository, https://github.com/Fogapod/pink-accents
Author-email: Fogapod <fogaprod@gmail.com>
Maintainer-email: Fogapod <fogaprod@gmail.com>
License-Expression: MIT
License-File: LICENSE
Keywords: accents,pattern-replacements,regex
Classifier: Development Status :: 4 - Beta
Classifier: Intended Audience :: Developers
Classifier: License :: OSI Approved :: MIT License
Classifier: Natural Language :: English
Classifier: Operating System :: OS Independent
Classifier: Programming Language :: Python
Classifier: Programming Language :: Python :: 3
Classifier: Programming Language :: Python :: 3.10
Classifier: Programming Language :: Python :: 3.11
Classifier: Programming Language :: Python :: 3.12
Classifier: Programming Language :: Python :: Implementation :: CPython
Classifier: Topic :: Text Processing
Classifier: Typing :: Typed
Requires-Python: >=3.10
Provides-Extra: dev
Requires-Dist: mypy==1.8.0; extra == 'dev'
Requires-Dist: pytest-cov==4.1.0; extra == 'dev'
Requires-Dist: pytest==8.0.1; extra == 'dev'
Requires-Dist: ruff==0.2.2; extra == 'dev'
